{
  "hash": "e5171fc9",
  "configHash": "fb88361f",
  "lockfileHash": "e71aab05",
  "browserHash": "ec6a111a",
  "optimized": {
    "vue": {
      "src": "../../../../node_modules/vue/dist/vue.runtime.esm-bundler.js",
      "file": "vue.js",
      "fileHash": "4e876bd1",
      "needsInterop": false
    },
    "vitepress > @vue/devtools-api": {
      "src": "../../../../node_modules/@vue/devtools-api/dist/index.js",
      "file": "vitepress___@vue_devtools-api.js",
      "fileHash": "49eaff83",
      "needsInterop": false
    },
    "vitepress > @vueuse/core": {
      "src": "../../../../node_modules/@vueuse/core/index.mjs",
      "file": "vitepress___@vueuse_core.js",
      "fileHash": "f7452fe6",
      "needsInterop": false
    },
    "@theme/index": {
      "src": "../../../../node_modules/vitepress/dist/client/theme-default/index.js",
      "file": "@theme_index.js",
      "fileHash": "70b26fe6",
      "needsInterop": false
    }
  },
  "chunks": {
    "chunk-3GYA4YLH": {
      "file": "chunk-3GYA4YLH.js"
    },
    "chunk-DDXJJ377": {
      "file": "chunk-DDXJJ377.js"
    }
  }
}